<teiCorpus xmlns="http://www.tei-c.org/ns/1.0">
    <teiHeader>
        <fileDesc>
            <titleStmt>
                <title>Catalogo Cicognara Number 1452</title>
            </titleStmt>
            <publicationStmt>
                <publisher>
                    <orgName>Digital Cicognara Library</orgName>
                    <ref>https://cicognara.org</ref>
                </publisher>
                <idno type="cico">1452</idno>
            </publicationStmt>
            <sourceDesc>
                <bibl>
                    <author>VALDOR Jean</author>, <title>Les triomphe de Louis le Juste XIII du nom roi de France et de Navarre avec
    les portraits du roi, princes etc. etc. et leurs devises en forme d’eloge par Henry Êtienne</title>,
<fw type="foot"/>
                  <pb type="memofonte"/>
                  <fw type="head"/>
    
    traduit en latin par le P. Nicolai, <pubPlace>Paris</pubPlace> <date>1649</date>, in fol. fig. francese e latino. Ouvrage entrepris et
    fini par Jean Valdor calcographe du roi.
    <note>Opera copiosissima di bellissimi ritratti imprese ed altre stampe allegoriche frapposte al testo; il quale parimente
    è eseguito con molto splendore di tipi.</note>
    MDCLI
    
    </bibl>
            </sourceDesc>
        </fileDesc>
    </teiHeader>
</teiCorpus>