<teiCorpus xmlns="http://www.tei-c.org/ns/1.0">
    <teiHeader>
        <fileDesc>
            <titleStmt>
                <title>Catalogo Cicognara Number 1818</title>
            </titleStmt>
            <publicationStmt>
                <publisher>
                    <orgName>Digital Cicognara Library</orgName>
                    <ref>https://cicognara.org</ref>
                </publisher>
                <idno type="cico">1818</idno>
            </publicationStmt>
            <sourceDesc>
                <bibl>
                    <author>VAVASSORE detto Guadagnino Giovanni Andrea</author>, <title>Esemplario novo di più di cento variate
                     mostre di qualunque sorte bellissime per cucire intitulato Fontana de gli esempli</title>, <date>1550</date>, in 4,
  obl.
  <fw type="foot"/>
                  <pb type="memofonte"/>
                  <fw type="head"/>
  <note>Nel frontespizio è una fontana col motto Sollicitudo est mater divitiarum, e lateralmente Donne e donzelle che el
  cusir segnile (per farvi eterne alla fonte venite) a retro del frontesp. sta la dedica cosi intestata. Il Pelliciolo alta
  molto magnifica Madonna Lippomana Signora e Padrona Osservandissima, dopo la quale finisce la pagina con
  un sonetto. Seguono quattordici foglietti impressi da ambo i lati con 28 disegni intagliati in legno di vari punti e
  ricami e nel foglio ultimo dopo questi è un avviso ALLE VIRTUOSE DONNE et a qualunque lettore Giovan Andrea
  Vavassore detto Guadagnino. Nuovamen <pb type="cico" n="311"/>te stampato ec. Le prime opere prodotte da questo intagliatore e
  tipografo erano assai più rozze (Vedi la sua Biblia Pauperum). Ma siccome precedono di molli anni questa
  ristampa, fatta però lui vivente, si scorge l’avanzamento ch’egli aveva fatto nell’arte sua. Vedi agli articoli
  Bellezze, Vinciolo, Passerotti.</note>
  
  </bibl>
            </sourceDesc>
        </fileDesc>
    </teiHeader>
</teiCorpus>