<teiCorpus xmlns="http://www.tei-c.org/ns/1.0">
    <teiHeader>
        <fileDesc>
            <titleStmt>
                <title>Catalogo Cicognara Number 1862</title>
            </titleStmt>
            <publicationStmt>
                <publisher>
                    <orgName>Digital Cicognara Library</orgName>
                    <ref>https://cicognara.org</ref>
                </publisher>
                <idno type="cico">1862</idno>
            </publicationStmt>
            <sourceDesc>
                <bibl>
                    <author>BRY (DE) Teodori</author>, <title>Proscenium vitae humanae sive emblematum saecularium iucundissima et
    artificiosissima varietate vitae humanae etc. etc. versibus latinis, germanicis, gallicis et
    belgicis etc. decades septem</title>, <pubPlace>Francf.</pubPlace>, per <publisher>Theod. de Bry</publisher>, <date>1621</date>, in 8.
    Con elegantissime e rare incisioni in 74 tavole, delle quali una è il frontespizio, l’altra il typus amicitiae e 71 gli
    emblemi. Libro difficile a trovarsi senza mutilazioni per i soggetti liberi in esso espressi.
    
    </bibl>
            </sourceDesc>
        </fileDesc>
    </teiHeader>
</teiCorpus>