<teiCorpus xmlns="http://www.tei-c.org/ns/1.0">
    <teiHeader>
        <fileDesc>
            <titleStmt>
                <title>Catalogo Cicognara Number 2502</title>
            </titleStmt>
            <publicationStmt>
                <publisher>
                    <orgName>Digital Cicognara Library</orgName>
                    <ref>https://cicognara.org</ref>
                </publisher>
                <idno type="cico">2502</idno>
            </publicationStmt>
            <sourceDesc>
                <bibl>
                    <author>SALMASII Claudii</author>, <title>Plinianae exercitationes in Caji Julii Solini Polyhistora: item Caji Julii Solini Polyhistor ex
veteribus libris emendatus</title>, <pubPlace>Parisiis</pubPlace> <date>1629</date>, in fol., vol. 2.
<note>Quest’opera è commendevole per la critica con cui è scritta e per le nozioni d’antichità e di arti che vi si trovano,
illustrando molti luoghi di Plinio e di Vitruvio.</note>
</bibl>
            </sourceDesc>
        </fileDesc>
    </teiHeader>
</teiCorpus>