<teiCorpus xmlns="http://www.tei-c.org/ns/1.0">
    <teiHeader>
        <fileDesc>
            <titleStmt>
                <title>Catalogo Cicognara Number 3726</title>
            </titleStmt>
            <publicationStmt>
                <publisher>
                    <orgName>Digital Cicognara Library</orgName>
                    <ref>https://cicognara.org</ref>
                </publisher>
                <idno type="cico">3726</idno>
            </publicationStmt>
            <sourceDesc>
                <bibl>
                    <author>FIGRELII Edmundi</author>, <title>Accedit Schefferi Joan, De antiquorum torquibus</title>, <pubPlace>Holmiae</pubPlace> <date>1656</date>, fig.
<note>La prima di queste due opere stampata in carta ottima apparisce di una miglior edizione, sebbene siano gli stessi
tipi. Amendue le opere sono pregievolissime.</note>
</bibl>
            </sourceDesc>
        </fileDesc>
    </teiHeader>
</teiCorpus>