<teiCorpus xmlns="http://www.tei-c.org/ns/1.0">
    <teiHeader>
        <fileDesc>
            <titleStmt>
                <title>Catalogo Cicognara Number 3829</title>
            </titleStmt>
            <publicationStmt>
                <publisher>
                    <orgName>Digital Cicognara Library</orgName>
                    <ref>https://cicognara.org</ref>
                </publisher>
                <idno type="cico">3829</idno>
            </publicationStmt>
            <sourceDesc>
                <bibl>
                    <author>PIRANESI Giovan Battista </author> architetto veneziano, <title>Vedute di Roma disegnate, ed incise</title>.
<note>Questo potrebbe essere un quinto volume alle antichità romane se non fossero quivi intagliate anche alcune
fabbriche moderne in 54 tavole, compreso il frontespizio.</note>
</bibl>
            </sourceDesc>
        </fileDesc>
    </teiHeader>
</teiCorpus>