<teiCorpus xmlns="http://www.tei-c.org/ns/1.0">
    <teiHeader>
        <fileDesc>
            <titleStmt>
                <title>Catalogo Cicognara Number 4060</title>
            </titleStmt>
            <publicationStmt>
                <publisher>
                    <orgName>Digital Cicognara Library</orgName>
                    <ref>https://cicognara.org</ref>
                </publisher>
                <idno type="cico">4060</idno>
            </publicationStmt>
            <sourceDesc>
                <bibl>
                    <author>PAOLINO da S. Bartolommeo</author>, <title>Viaggio alle Indie Orientali umiliato alla Santità di Pio VI</title>, 
                        <publisher>Roma</publisher> <date>1796</date>, in 4, fig.
<note>Sono alcune tavole collocate fra il testo. Opera non dettata da buona critica.</note>
</bibl>
            </sourceDesc>
        </fileDesc>
    </teiHeader>
</teiCorpus>