<teiCorpus xmlns="http://www.tei-c.org/ns/1.0">
    <teiHeader>
        <fileDesc>
            <titleStmt>
                <title>Catalogo Cicognara Number 4533</title>
            </titleStmt>
            <publicationStmt>
                <publisher>
                    <orgName>Digital Cicognara Library</orgName>
                    <ref>https://cicognara.org</ref>
                </publisher>
                <idno type="cico">4533</idno>
            </publicationStmt>
            <sourceDesc>
                <bibl>
                    <title>CATALOGUE d’un excellent et precieux Cabinet de Desseins: provenants du Cabinet de M. John Bernard, dans la
vente faite en <date>1787</date>
                    </title>, <pubPlace>Londres</pubPlace>, in 8.
</bibl>
            </sourceDesc>
        </fileDesc>
    </teiHeader>
</teiCorpus>