<teiCorpus xmlns="http://www.tei-c.org/ns/1.0">
    <teiHeader>
        <fileDesc>
            <titleStmt>
                <title>Catalogo Cicognara Number 4634</title>
            </titleStmt>
            <publicationStmt>
                <publisher>
                    <orgName>Digital Cicognara Library</orgName>
                    <ref>https://cicognara.org</ref>
                </publisher>
                <idno type="cico">4634</idno>
            </publicationStmt>
            <sourceDesc>
                <bibl> <title>BIBLIOTHECA Stoschiana, seu catalogus selectissimorum librorum quos collegerat Philippus Liber Baro de
Stosch</title>, <pubPlace>Florentiae</pubPlace> <date>1759</date>, in 8.
<fw type="foot"/>
                     <pb type="memofonte"/>
                     <fw type="head"/>
                  </bibl>
            </sourceDesc>
        </fileDesc>
    </teiHeader>
</teiCorpus>