<teiCorpus xmlns="http://www.tei-c.org/ns/1.0">
    <teiHeader>
        <fileDesc>
            <titleStmt>
                <title>Catalogo Cicognara Number 4647</title>
            </titleStmt>
            <publicationStmt>
                <publisher>
                    <orgName>Digital Cicognara Library</orgName>
                    <ref>https://cicognara.org</ref>
                </publisher>
                <idno type="cico">4647</idno>
            </publicationStmt>
            <sourceDesc>
                <bibl>
                    <author>CLARK</author>, <title>Repertorium bibliographicum</title>, <pubPlace>London</pubPlace> <date>1819</date>, vol. 2, in 4.
<note>Opera superficiale, ove si tratta di alcuni preziosi libri posseduti da diversi amatori di curiosità in Inghilterra, e
ricco di molti bei ritratti intagliati in rame.</note>
</bibl>
            </sourceDesc>
        </fileDesc>
    </teiHeader>
</teiCorpus>