<teiCorpus xmlns="http://www.tei-c.org/ns/1.0">
    <teiHeader>
        <fileDesc>
            <titleStmt>
                <title>Catalogo Cicognara Number 4772</title>
            </titleStmt>
            <publicationStmt>
                <publisher>
                    <orgName>Digital Cicognara Library</orgName>
                    <ref>https://cicognara.org</ref>
                </publisher>
                <idno type="cico">4772</idno>
            </publicationStmt>
            <sourceDesc>
                <bibl>
                    <title>DESCRIPTION of Fonthill Abbey Wiltshire with views</title>, <pubPlace>London</pubPlace> <date>1817</date>, in 8.
<note>Questa descrizione della villa del cavalier William Beckford è tanto più preziosa quanto è maggiore la difficoltà
di vedere questo luogo magnifico e pittoresco. Il libro è ornato da 9 tavole di finissimo intaglio, e termina con
alcuni cenni su i più singolari libri della biblioteca di quel palazzo.</note>
</bibl>
            </sourceDesc>
        </fileDesc>
    </teiHeader>
</teiCorpus>