<teiCorpus xmlns="http://www.tei-c.org/ns/1.0">
    <teiHeader>
        <fileDesc>
            <titleStmt>
                <title>Catalogo Cicognara Number 636</title>
            </titleStmt>
            <publicationStmt>
                <publisher>
                    <orgName>Digital Cicognara Library</orgName>
                    <ref>https://cicognara.org</ref>
                </publisher>
                <idno type="cico">636</idno>
            </publicationStmt>
            <sourceDesc>
                <bibl> 
                     <author>ROSSI Domenico</author>, 
                     <title>Studio d’architettura civile, V Cataneo Pietro, cui va unito.</title>
                  </bibl>
            </sourceDesc>
        </fileDesc>
    </teiHeader>
</teiCorpus>